cdktf_cdktf_provider_null/__init__.py
cdktf_cdktf_provider_null/py.typed
cdktf_cdktf_provider_null/_jsii/__init__.py
cdktf_cdktf_provider_null/_jsii/provider-null@11.0.0.jsii.tgz
cdktf_cdktf_provider_null/data_null_data_source/__init__.py
cdktf_cdktf_provider_null/provider/__init__.py
cdktf_cdktf_provider_null/resource/__init__.py
cdktf_cdktf_provider_null-11.0.0.dist-info/LICENSE
cdktf_cdktf_provider_null-11.0.0.dist-info/METADATA
cdktf_cdktf_provider_null-11.0.0.dist-info/WHEEL
cdktf_cdktf_provider_null-11.0.0.dist-info/top_level.txt
cdktf_cdktf_provider_null-11.0.0.dist-info/RECORD
